LICENSE
README.md
setup.py
FastSocket/FastSocket.py
FastSocket/__init__.py
FastSocket/_expt.py
FastSocket/_types.py
FastSocket/fastsocket.py
FastSocket/logger.py
FastSocket/security.py
FastSocket.egg-info/PKG-INFO
FastSocket.egg-info/SOURCES.txt
FastSocket.egg-info/dependency_links.txt
FastSocket.egg-info/requires.txt
FastSocket.egg-info/top_level.txt
fastsocket/__init__.py
fastsocket/_expt.py
fastsocket/_types.py
fastsocket/fastsocket.py