Metadata-Version: 2.1
Name: FastSocket
Version: 1.0.5
Summary: This library is intended to create fast TCP and UDP server/client with multi connection handling.
Home-page: https://github.com/giulicrenna/FastSocket
Author: Giuliano Crenna
Author-email: giulicrenna@gmail.com
Classifier: Programming Language :: Python :: 3
Classifier: License :: OSI Approved :: GNU Affero General Public License v3 or later (AGPLv3+)
Classifier: Operating System :: OS Independent
Classifier: Topic :: Software Development :: Libraries
License-File: LICENSE
